wimprates/__init__.py
wimprates/bremsstrahlung.py
wimprates/elastic_nr.py
wimprates/electron.py
wimprates/halo.py
wimprates/migdal.py
wimprates/summary.py
wimprates/utils.py
wimprates/data/bs/REFERENCE
wimprates/data/bs/atomic_form_1
wimprates/data/bs/atomic_form_2
wimprates/data/dme/REFERENCE
wimprates/data/dme/dme_ionization_ff.pkl
wimprates/data/migdal/REFERENCE
wimprates/data/migdal/Xe.dat
wimprates/data/migdal/dat_to_cvs.py
wimprates/data/migdal/migdal_transition_Ar.csv
wimprates/data/migdal/migdal_transition_Ge.csv
wimprates/data/migdal/migdal_transition_Si.csv
wimprates/data/migdal/migdal_transition_Xe.csv
wimprates/data/sd/abundances
wimprates/data/sd/structure_f_erec_xe.pkl
wimprates-0.5.0.dist-info/LICENSE
wimprates-0.5.0.dist-info/METADATA
wimprates-0.5.0.dist-info/WHEEL
wimprates-0.5.0.dist-info/top_level.txt
wimprates-0.5.0.dist-info/RECORD
