Metadata-Version: 2.1
Name: wimprates
Version: 0.5.0
Summary: Differential rates of WIMP-nucleus scattering
Home-page: https://github.com/jelleaalbers/wimprates
Author: Jelle Aalbers
License: MIT
Keywords: wimp,spin-dependent,spin-independent,bremsstrahlung,migdal
Classifier: Intended Audience :: Science/Research
Classifier: Development Status :: 3 - Alpha
Classifier: Programming Language :: Python
Classifier: Programming Language :: Python :: 3
License-File: LICENSE
Requires-Dist: numpy
Requires-Dist: scipy
Requires-Dist: pandas
Requires-Dist: tqdm
Requires-Dist: boltons
Requires-Dist: numericalunits
